maquette/__init__.py
maquette/__mq.py
maquette/__workspaces.py
maquette/cli.py
maquette/common/__errors.py
maquette_lib/__client.py
maquette_lib/__code_repository_config.py
maquette_lib/__init__.py
maquette_lib/__user_config.py
maquette-0.1.7.dist-info/entry_points.txt
maquette-0.1.7.dist-info/WHEEL
maquette-0.1.7.dist-info/METADATA
maquette-0.1.7.dist-info/RECORD
